Metadata-Version: 1.1
Name: Chern
Version: 3.1.1
Summary: A data analysis management toolkit for high energy physics
Home-page: https://github.com/zhaomr13/Chern
Author: Mingrui Zhao
Author-email: mingrui.zhao@mail.labz0.org
License: Apache License, Version 2.0
Keywords: Analysis Perservation
Platform: UNKNOWN
Classifier: Development Status :: 3 - Alpha
Classifier: Intended Audience :: Science/Research
Classifier: Topic :: Scientific/Engineering :: Physics
Classifier: Programming Language :: Python :: 3
Classifier: Programming Language :: Python :: Implementation :: CPython
